{
  "instance": "inst_set1a_sf0_nc2.1_n20_m20_05.dzn",
  "results": {
    "SPT": {
      "max_flow": 0,
      "ordered_activities": [
        2,
        5,
        7,
        9,
        3,
        12,
        6,
        11,
        4,
        13,
        8,
        10,
        16,
        15,
        18,
        20,
        17,
        19,
        14,
        21
      ]
    },
    "LPT": {
      "max_flow": 0,
      "ordered_activities": [
        4,
        3,
        8,
        2,
        6,
        5,
        11,
        14,
        10,
        15,
        7,
        17,
        13,
        9,
        19,
        16,
        21,
        20,
        18,
        12
      ]
    },
    "MST": {
      "max_flow": 0,
      "ordered_activities": [
        2,
        9,
        5,
        11,
        7,
        3,
        12,
        4,
        13,
        8,
        10,
        15,
        14,
        17,
        19,
        6,
        16,
        18,
        20,
        21
      ]
    }
  },
  "best_algorithm": "MST",
  "best_max_flow": 0
}